failures/__init__.py
failures/core.py
failures/functions.py
failures/handler.py
failures/py.typed
failures-1.0.1.dist-info/LICENSE
failures-1.0.1.dist-info/METADATA
failures-1.0.1.dist-info/WHEEL
failures-1.0.1.dist-info/top_level.txt
failures-1.0.1.dist-info/RECORD
