Metadata-Version: 2.1
Name: failures
Version: 1.0.1
Summary: Successfully dealing with failures
Author-email: MARSO Adnan <mediadnan@gmail.com>
Maintainer-email: MARSO Adnan <mediadnan@gmail.com>
License: MIT License
Project-URL: documentation, https://failures.readthedocs.org
Project-URL: repository, https://github.com/mediadnan/failures
Keywords: label,failures,handle,handling,report,track
Classifier: License :: OSI Approved :: MIT License
Classifier: Development Status :: 5 - Production/Stable
Classifier: Programming Language :: Python
Classifier: Programming Language :: Python :: 3
Classifier: Programming Language :: Python :: 3 :: Only
Classifier: Programming Language :: Python :: 3.8
Classifier: Programming Language :: Python :: 3.9
Classifier: Programming Language :: Python :: 3.10
Classifier: Programming Language :: Python :: 3.11
Classifier: Topic :: Utilities
Classifier: Typing :: Typed
Requires-Python: >=3.8
License-File: LICENSE
Requires-Dist: typing-extensions ==4.5.0
Provides-Extra: colors
Requires-Dist: colorama <1.0,>=0.4 ; extra == 'colors'
Requires-Dist: types-colorama ; extra == 'colors'
